rootf/__init__.py
rootf/cli.py
rootf/config.py
rootf/config.yaml
rootf/system_info.py
rootf/ascii_art/__init__.py
rootf/tests/__init__.py
rootf/tests/test_system_info.py
rootf-0.1.6.dist-info/entry_points.txt
rootf-0.1.6.dist-info/licenses/LICENSE
rootf-0.1.6.dist-info/WHEEL
rootf-0.1.6.dist-info/METADATA
rootf-0.1.6.dist-info/RECORD
