Metadata-Version: 2.4
Name: rootf
Version: 0.1.6
Summary: A system information tool similar to neofetch
Keywords: system-information,neofetch,cli
Author-email: nloveuser <nloveuser@nloveuser.ru>
Requires-Python: >=3.8
Classifier: Programming Language :: Python :: 3
Classifier: License :: OSI Approved :: MIT License
Classifier: Operating System :: OS Independent
License-File: LICENSE
Requires-Dist: psutil>=5.9.0
Requires-Dist: platformdirs>=2.5.0
Requires-Dist: pyyaml>=6.0.0
Requires-Dist: requests>=2.28.0
